[{"tmdbId":14709,"guideBoxId":37066,"title":"Varsity Blues","year":1999,"genre":"Comedy, Drama, Romance","director":"Brian Robbins","actors":"James Van Der Beek, Jon Voight, Paul Walker, Ron Lester","poster":"http://image.tmdb.org/t/p/w185/nnVA3Nmry9furen0NDmJa0QTn2F.jpg","trailer":"https://www.youtube.com/watch?v=eSnkWiacUW4","rec1":"Major League II, 11067, http://image.tmdb.org/t/p/w500/yTKCbUU67aHmqqy7ZiPvpPLiYvE.jpg","rec2":"The New Guy, 10985, http://image.tmdb.org/t/p/w500/uqUVToyQmcqBqm7USWEQIYDNERd.jpg","rec3":"Edtv, 11374, http://image.tmdb.org/t/p/w500/sF3YBtYn6yAHMPDbiC58WArIWMl.jpg","created_at":"2017-05-07T19:28:46.000Z"},{"tmdbId":109445,"guideBoxId":90293,"title":"Frozen","year":2013,"genre":"Animation, Adventure, Comedy","director":"Chris Buck, Jennifer Lee","actors":"Kristen Bell, Idina Menzel, Jonathan Groff, Josh Gad","poster":"http://image.tmdb.org/t/p/w185/jIjdFXKUNtdf1bwqMrhearpyjMj.jpg","trailer":"https://www.youtube.com/watch?v=-WdC4DaYIeQ","rec1":"Tangled, 38757, http://image.tmdb.org/t/p/w500/re6AOJbhBk9FIK3knwU6rYlbPDx.jpg","rec2":"Maleficent, 102651, http://image.tmdb.org/t/p/w500/4FYu1AAu14tuBU0lns0hbKiHUcH.jpg","rec3":"How to Train Your Dragon 2, 82702, http://image.tmdb.org/t/p/w500/lRjOR4uclMQijUav4OjeZprlehu.jpg","created_at":"2017-05-07T19:28:37.000Z"}]